{"cookies": [], "origins": [{"origin": "https://nikita-filonov.github.io", "localStorage": [{"name": "persist:users", "value": "{\"user\":\"{\\\"id\\\":\\\"4b83143b-36d3-4d6d-adf8-ae4c89ba709d\\\",\\\"email\\\":\\\"my_user123@gmail.com\\\",\\\"username\\\":\\\"my_user123\\\",\\\"password\\\":\\\"12345\\\"}\",\"users\":\"[{\\\"id\\\":\\\"4b83143b-36d3-4d6d-adf8-ae4c89ba709d\\\",\\\"email\\\":\\\"my_user123@gmail.com\\\",\\\"username\\\":\\\"my_user123\\\",\\\"password\\\":\\\"12345\\\"}]\",\"_persist\":\"{\\\"version\\\":-1,\\\"rehydrated\\\":true}\"}"}, {"name": "persist:courses", "value": "{\"course\":\"{\\\"id\\\":\\\"\\\",\\\"title\\\":\\\"\\\",\\\"userId\\\":\\\"\\\",\\\"maxScore\\\":0,\\\"minScore\\\":0,\\\"exercises\\\":[],\\\"description\\\":\\\"\\\",\\\"previewImage\\\":null,\\\"estimatedTime\\\":\\\"\\\"}\",\"courses\":\"[]\",\"_persist\":\"{\\\"version\\\":-1,\\\"rehydrated\\\":true}\"}"}]}]}